pypsbuilder/__init__.py
pypsbuilder/psbuilders.py
pypsbuilder/psclasses.py
pypsbuilder/psexplorer.py
pypsbuilder/tcapi.py
pypsbuilder/tcinit.py
pypsbuilder/ui_addinv.py
pypsbuilder/ui_adduni.py
pypsbuilder/ui_ptbuilder.py
pypsbuilder/ui_pxbuilder.py
pypsbuilder/ui_txbuilder.py
pypsbuilder/ui_uniguess.py
pypsbuilder/images/ptbuilder.png
pypsbuilder/images/pxbuilder.png
pypsbuilder/images/pypsbuilder.png
pypsbuilder/images/txbuilder.png
pypsbuilder/tests/__init__.py
pypsbuilder/tests/test_pclasses.py
pypsbuilder/ui/addinv.ui
pypsbuilder/ui/adduni.ui
pypsbuilder/ui/compile_ui.sh
pypsbuilder/ui/ptbuilder.ui
pypsbuilder/ui/pxbuilder.ui
pypsbuilder/ui/txbuilder.ui
pypsbuilder/ui/uniguess.ui
pypsbuilder-2.6.4.dist-info/METADATA
pypsbuilder-2.6.4.dist-info/WHEEL
pypsbuilder-2.6.4.dist-info/entry_points.txt
pypsbuilder-2.6.4.dist-info/licenses/AUTHORS.md
pypsbuilder-2.6.4.dist-info/licenses/LICENSE
pypsbuilder-2.6.4.dist-info/RECORD
