Metadata-Version: 2.4
Name: pypsbuilder
Version: 2.6.4
Summary: THERMOCALC front-end for constructing and analyzing PT pseudosections
Project-URL: Homepage, https://github.com/ondrolexa/pypsbuilder
Project-URL: Documentation, https://pypsbuilder.readthedocs.io
Project-URL: Repository, https://github.com/ondrolexa/pypsbuilder.git
Project-URL: Issues, https://github.com/ondrolexa/pypsbuilder/issues
Project-URL: Changelog, https://github.com/ondrolexa/pypsbuilder/blob/master/CHANGELOG.md
Author-email: Ondrej Lexa <lexa.ondrej@gmail.com>
Maintainer-email: Ondrej Lexa <lexa.ondrej@gmail.com>
License: MIT License
License-File: AUTHORS.md
License-File: LICENSE
Keywords: THERMOCALC,petrology
Classifier: Development Status :: 4 - Beta
Classifier: Intended Audience :: Science/Research
Classifier: Programming Language :: Python :: 3
Classifier: Programming Language :: Python :: 3 :: Only
Classifier: Programming Language :: Python :: 3.10
Classifier: Topic :: Scientific/Engineering
Classifier: Topic :: Utilities
Requires-Python: >=3.10
Requires-Dist: matplotlib>=3.8
Requires-Dist: networkx
Requires-Dist: numpy
Requires-Dist: qtpy
Requires-Dist: scikit-image
Requires-Dist: scipy
Requires-Dist: shapely>=2
Requires-Dist: tqdm
Provides-Extra: dev
Requires-Dist: black; extra == 'dev'
Requires-Dist: jupyterlab; extra == 'dev'
Requires-Dist: pyqt6; extra == 'dev'
Requires-Dist: pytest; extra == 'dev'
Requires-Dist: pytest-cov; extra == 'dev'
Requires-Dist: sphinx; extra == 'dev'
Requires-Dist: sphinx-mdinclude; extra == 'dev'
Requires-Dist: sphinx-rtd-theme; extra == 'dev'
Provides-Extra: docs
Requires-Dist: sphinx; extra == 'docs'
Requires-Dist: sphinx-mdinclude; extra == 'docs'
Requires-Dist: sphinx-rtd-theme; extra == 'docs'
Provides-Extra: jupyter
Requires-Dist: jupyterlab; extra == 'jupyter'
Provides-Extra: pyqt5
Requires-Dist: pyqt5; extra == 'pyqt5'
Provides-Extra: pyqt6
Requires-Dist: pyqt6; extra == 'pyqt6'
Provides-Extra: tests
Requires-Dist: pytest; extra == 'tests'
Requires-Dist: pytest-cov; extra == 'tests'
